markdown_image_caption/__init__.py
markdown_image_caption/plugin.py
markdown_image_caption-0.3.0.dist-info/METADATA
markdown_image_caption-0.3.0.dist-info/WHEEL
markdown_image_caption-0.3.0.dist-info/top_level.txt
markdown_image_caption-0.3.0.dist-info/RECORD
