Metadata-Version: 2.1
Name: markdown-image-caption
Version: 0.3.0
Summary: Image caption support for Python Markdown
Home-page: UNKNOWN
Author: Sander Teunissen
Author-email: 
License: MIT
Platform: UNKNOWN
Classifier: License :: OSI Approved :: MIT License
Classifier: Programming Language :: Python
Classifier: Programming Language :: Python :: 3.5
Classifier: Programming Language :: Python :: 3.6
Classifier: Programming Language :: Python :: Implementation :: CPython
Classifier: Programming Language :: Python :: Implementation :: PyPy
